LICENSE
README.md
pyproject.toml
setup.cfg
setup.py
pydwcviz/__init__.py
pydwcviz/utils.py
pydwcviz.egg-info/PKG-INFO
pydwcviz.egg-info/SOURCES.txt
pydwcviz.egg-info/dependency_links.txt
pydwcviz.egg-info/requires.txt
pydwcviz.egg-info/top_level.txt
pydwcviz/diversity/__init__.py
pydwcviz/diversity/diversity.py
pydwcviz/diversity/test_diversity.py
pydwcviz/map/__init__.py
pydwcviz/map/map.py
pydwcviz/stats/__init__.py
pydwcviz/stats/stats.py
pydwcviz/stats/test_stats.py
pydwcviz/taxon/__init__.py
pydwcviz/taxon/taxon.py
pydwcviz/taxon/test_taxon.py